Metadata-Version: 1.0
Name: bgg-distribution
Version: 0.1
Summary: Gaussian distributions
Home-page: UNKNOWN
Author: Noe Durocher
Author-email: UNKNOWN
License: UNKNOWN
Platform: UNKNOWN
